README.md
license.txt
setup.py
Compare_It/CompareIt.py
Compare_It/__init__.py
Compare_It/_old.py
Compare_It/compare_it_model.py
Compare_It/const.py
homeline.egg-info/PKG-INFO
homeline.egg-info/SOURCES.txt
homeline.egg-info/dependency_links.txt
homeline.egg-info/requires.txt
homeline.egg-info/top_level.txt