Metadata-Version: 2.1
Name: homeline
Version: 2.0.2
Summary: Wrapper for the Compare It Homeline Api
Author: Magnus Eldén
License-File: license.txt
